{
  "0": {
    "name": "Introduction to VLSI",
    "links": {
      "1": "./html/Module 1.html",
      "2": "./html/Module 1 PPT.html"
    }
  },
  "1": {
    "name": "Circuit Design Processes & CMOS Sub System Design",
    "links": {
      "1": "./html/Module 2 PPT-1.html",
      "2": "./html/Steps for CMOS.html",
      "3": "./html/Module 2 - 2.html"
    }
  },
  "2": {
    "name": "CMOS Logic Circuit Design",

    "links": {
      "1": "./html/Module 3.html",
      "2": "./html/Module 3 - 1.html",
      "3": "./html/Module 3 - 2.html"
    }
  },
  "3": {
    "name": "Advanced CMOS Logic Structures",

    "links": {
      "1": "./html/Module 4.html",
      "2": "./html/Module 4 Part 1.html",
      "3": "./html/Module 4 Part 2.html"
    }
  },
  "4": {
    "name": "MOS Amplifier, Differential Amplifier & Current Mirrors",

    "links": {
      "1": "./html/Module 5.html",
      "2": "./html/Module 5.1.html",
      "3": "./html/Module 5.2.html",
      "4": "./html/Differential Amplifier.html",
      "5": "./html/Single Stage amplifiers.html"
    }
  },
  "5": {
    "name": "Text Book & Lab Manual",

    "links": {
      "1": "./html/Lab Manual.html",
      "2": "./html/VLSI CIE3 QP 2021.html",
      "3": "./html/Text Book.html"
    }
  }
}
